jrequests/__init__.py
jrequests/py.typed
jrequests/request.py
jrequests-2025.2.1.dist-info/METADATA
jrequests-2025.2.1.dist-info/WHEEL
jrequests-2025.2.1.dist-info/top_level.txt
jrequests-2025.2.1.dist-info/RECORD
