Metadata-Version: 2.2
Name: jrequests
Version: 2025.2.1
Summary: A package providing Java's Jackson-like object mapping from REST request responses.
Author: Cristian Trohin
Author-email: Cristian Trohin <cristi.trohin@gmail.com>
Project-URL: Homepage, https://github.com/ctrohin/jrequests
Project-URL: Issues, https://github.com/ctrohin/jrequests/issues
Classifier: Programming Language :: Python :: 3
Classifier: License :: OSI Approved :: MIT License
Classifier: Operating System :: OS Independent
Requires-Python: >=3.9
Dynamic: author
